{
  "$id" : "https://raw.githubusercontent.com/BHoM/BHoM_JSONSchema/develop/Spatial_oM/Layouts/ICurveLayout.json",
  "required" : ["_t"],
  "properties" : {
    "_t" : {
      "enum" : ["BH.oM.Spatial.Layouts.OffsetCurveLayout", "BH.oM.Spatial.Layouts.ExplicitCurveLayout"]
    }
  },
  "allOf" : [{
      "if" : {
        "properties" : {
          "_t" : {
            "type" : ["string", "null"],
            "const" : "BH.oM.Spatial.Layouts.OffsetCurveLayout"
          }
        }
      },
      "then" : {
        "$ref" : "https://raw.githubusercontent.com/BHoM/BHoM_JSONSchema/develop/Spatial_oM/Layouts/OffsetCurveLayout.json"
      }
    }, {
      "if" : {
        "properties" : {
          "_t" : {
            "type" : ["string", "null"],
            "const" : "BH.oM.Spatial.Layouts.ExplicitCurveLayout"
          }
        }
      },
      "then" : {
        "$ref" : "https://raw.githubusercontent.com/BHoM/BHoM_JSONSchema/develop/Spatial_oM/Layouts/ExplicitCurveLayout.json"
      }
    }]
}