{
  "$schema" : "https://json-schema.org/draft/2020-12/schema",
  "$id" : "https://raw.githubusercontent.com/BHoM/BHoM_JSONSchema/develop/File_oM/SortOrder.json",
  "anyOf" : [{
      "type" : "string",
      "enum" : ["Default", "ByName", "BySize", "ByCreationTime", "ByLastModifiedTime"]
    }, {
      "type" : "object",
      "properties" : {
        "_t" : {
          "type" : "string",
          "const" : "System.Enum"
        },
        "TypeName" : {
          "type" : ["object", "null"],
          "properties" : {
            "_t" : {
              "type" : "string",
              "const" : "System.Type"
            },
            "Name" : {
              "type" : ["string", "null"],
              "const" : "BH.oM.Adapters.File.SortOrder"
            }
          }
        },
        "Value" : {
          "type" : "string",
          "enum" : ["Default", "ByName", "BySize", "ByCreationTime", "ByLastModifiedTime"]
        }
      }
    }]
}