{
  "$id" : "https://raw.githubusercontent.com/BHoM/BHoM_JSONSchema/v8.2/Verification_oM/Requirements/IRequirement.json",
  "required" : ["_t"],
  "properties" : {
    "_t" : {
      "const" : "BH.oM.Verification.Requirements.Requirement"
    }
  },
  "allOf" : [{
      "if" : {
        "properties" : {
          "_t" : {
            "type" : ["string", "null"],
            "const" : "BH.oM.Verification.Requirements.Requirement"
          }
        },
        "required" : ["_t"]
      },
      "then" : {
        "$ref" : "https://raw.githubusercontent.com/BHoM/BHoM_JSONSchema/v8.2/Verification_oM/Requirements/Requirement.json"
      }
    }]
}