{
  "$id" : "https://raw.githubusercontent.com/BHoM/BHoM_JSONSchema/v8.2/Spatial_oM/ShapeProfiles/CellularOpenings/ICellularOpening.json",
  "required" : ["_t"],
  "properties" : {
    "_t" : {
      "enum" : ["BH.oM.Spatial.ShapeProfiles.CellularOpenings.SinusoidalCellularOpening", "BH.oM.Spatial.ShapeProfiles.CellularOpenings.HexagonalCellularOpening", "BH.oM.Spatial.ShapeProfiles.CellularOpenings.CircularCellularOpening"]
    }
  },
  "allOf" : [{
      "if" : {
        "properties" : {
          "_t" : {
            "type" : ["string", "null"],
            "const" : "BH.oM.Spatial.ShapeProfiles.CellularOpenings.SinusoidalCellularOpening"
          }
        },
        "required" : ["_t"]
      },
      "then" : {
        "$ref" : "https://raw.githubusercontent.com/BHoM/BHoM_JSONSchema/v8.2/Spatial_oM/ShapeProfiles/CellularOpenings/SinusoidalCellularOpening.json"
      }
    }, {
      "if" : {
        "properties" : {
          "_t" : {
            "type" : ["string", "null"],
            "const" : "BH.oM.Spatial.ShapeProfiles.CellularOpenings.HexagonalCellularOpening"
          }
        },
        "required" : ["_t"]
      },
      "then" : {
        "$ref" : "https://raw.githubusercontent.com/BHoM/BHoM_JSONSchema/v8.2/Spatial_oM/ShapeProfiles/CellularOpenings/HexagonalCellularOpening.json"
      }
    }, {
      "if" : {
        "properties" : {
          "_t" : {
            "type" : ["string", "null"],
            "const" : "BH.oM.Spatial.ShapeProfiles.CellularOpenings.CircularCellularOpening"
          }
        },
        "required" : ["_t"]
      },
      "then" : {
        "$ref" : "https://raw.githubusercontent.com/BHoM/BHoM_JSONSchema/v8.2/Spatial_oM/ShapeProfiles/CellularOpenings/CircularCellularOpening.json"
      }
    }]
}