{
  "$id" : "https://raw.githubusercontent.com/BHoM/BHoM_JSONSchema/v8.2/Revit_oM/Elements/IInstance.json",
  "required" : ["_t"],
  "properties" : {
    "_t" : {
      "enum" : ["BH.oM.Adapters.Revit.Elements.ModelInstance", "BH.oM.Adapters.Revit.Elements.DraftingInstance"]
    }
  },
  "allOf" : [{
      "if" : {
        "properties" : {
          "_t" : {
            "type" : ["string", "null"],
            "const" : "BH.oM.Adapters.Revit.Elements.ModelInstance"
          }
        },
        "required" : ["_t"]
      },
      "then" : {
        "$ref" : "https://raw.githubusercontent.com/BHoM/BHoM_JSONSchema/v8.2/Revit_oM/Elements/ModelInstance.json"
      }
    }, {
      "if" : {
        "properties" : {
          "_t" : {
            "type" : ["string", "null"],
            "const" : "BH.oM.Adapters.Revit.Elements.DraftingInstance"
          }
        },
        "required" : ["_t"]
      },
      "then" : {
        "$ref" : "https://raw.githubusercontent.com/BHoM/BHoM_JSONSchema/v8.2/Revit_oM/Elements/DraftingInstance.json"
      }
    }]
}